yangson/__init__.py
yangson/__main__.py
yangson/constraint.py
yangson/convert8525.py
yangson/datamodel.py
yangson/datatype.py
yangson/enumerations.py
yangson/exceptions.py
yangson/instance.py
yangson/instroute.py
yangson/instvalue.py
yangson/nodeset.py
yangson/parser.py
yangson/schemadata.py
yangson/schemanode.py
yangson/schpattern.py
yangson/statement.py
yangson/typealiases.py
yangson/xmlparser.py
yangson/xpathast.py
yangson/xpathparser.py
yangson-1.6.6.dist-info/METADATA
yangson-1.6.6.dist-info/WHEEL
yangson-1.6.6.dist-info/entry_points.txt
yangson-1.6.6.dist-info/licenses/COPYING
yangson-1.6.6.dist-info/licenses/COPYING.LESSER
yangson-1.6.6.dist-info/RECORD
