Metadata-Version: 2.4
Name: yangson
Version: 1.6.6
Summary: Library for working with data modelled in YANG
License: GNU Lesser General Public License v3 (LGPLv3)
License-File: COPYING
License-File: COPYING.LESSER
Author: Ladislav Lhotka
Author-email: ladislav@lhotka.name
Requires-Python: >=3.9,<4.0
Classifier: License :: Other/Proprietary License
Classifier: Programming Language :: Python :: 3
Classifier: Programming Language :: Python :: 3.9
Classifier: Programming Language :: Python :: 3.10
Classifier: Programming Language :: Python :: 3.11
Classifier: Programming Language :: Python :: 3.12
Classifier: Programming Language :: Python :: 3.13
Classifier: Programming Language :: Python :: 3.14
Provides-Extra: yang-tools
Requires-Dist: PyYAML (>=6.0.1,<7.0.0)
Requires-Dist: elementpath (>=4.1.5,<5.0.0)
Requires-Dist: pyang (>=2.7.1,<3.0) ; extra == "yang-tools"
Requires-Dist: sphinxcontrib-shtest (>=0.5.0,<0.6.0)
